{
  "info": {
    "name": "Wixbot API",
    "_postman_id": "wixbot-collection-v1",
    "schema": "https://schema.getpostman.com/json/collection/v2.1.0/collection.json"
  },
  "variable": [
    {
      "key": "base_url",
      "value": "http://localhost:8000"
    },
    {
      "key": "access",
      "value": ""
    },
    {
      "key": "refresh",
      "value": ""
    },
    {
      "key": "bot_id",
      "value": ""
    },
    {
      "key": "source_id",
      "value": ""
    },
    {
      "key": "conv_id",
      "value": ""
    },
    {
      "key": "lead_id",
      "value": ""
    },
    {
      "key": "behavior_id",
      "value": ""
    }
  ],
  "item": [
    {
      "name": "1 - Auth",
      "item": [
        {
          "name": "Register",
          "request": {
            "method": "POST",
            "header": [
              {
                "key": "Content-Type",
                "value": "application/json",
                "type": "text"
              }
            ],
            "url": {
              "raw": "{{base_url}}/api/auth/register/",
              "host": [
                "{{base_url}}"
              ],
              "path": [
                "api",
                "auth",
                "register",
                ""
              ]
            },
            "body": {
              "mode": "raw",
              "raw": "{\n  \"email\": \"johal@test.com\",\n  \"password\": \"StrongPass123!\",\n  \"password2\": \"StrongPass123!\",\n  \"company_name\": \"Johal Store\"\n}",
              "options": {
                "raw": {
                  "language": "json"
                }
              }
            }
          },
          "response": []
        },
        {
          "name": "Verify Email",
          "request": {
            "method": "POST",
            "header": [
              {
                "key": "Content-Type",
                "value": "application/json",
                "type": "text"
              }
            ],
            "url": {
              "raw": "{{base_url}}/api/auth/verify-email/",
              "host": [
                "{{base_url}}"
              ],
              "path": [
                "api",
                "auth",
                "verify-email",
                ""
              ]
            },
            "body": {
              "mode": "raw",
              "raw": "{\n  \"email\": \"johal@test.com\",\n  \"otp\": \"1234\"\n}",
              "options": {
                "raw": {
                  "language": "json"
                }
              }
            }
          },
          "response": []
        },
        {
          "name": "Login",
          "request": {
            "method": "POST",
            "header": [
              {
                "key": "Content-Type",
                "value": "application/json",
                "type": "text"
              }
            ],
            "url": {
              "raw": "{{base_url}}/api/auth/login/",
              "host": [
                "{{base_url}}"
              ],
              "path": [
                "api",
                "auth",
                "login",
                ""
              ]
            },
            "body": {
              "mode": "raw",
              "raw": "{\n  \"email\": \"johal@test.com\",\n  \"password\": \"StrongPass123!\"\n}",
              "options": {
                "raw": {
                  "language": "json"
                }
              }
            }
          },
          "response": [],
          "event": [
            {
              "listen": "test",
              "script": {
                "exec": [
                  "const r = pm.response.json();",
                  "if(r.data && r.data.access){",
                  "  pm.environment.set('access', r.data.access);",
                  "  pm.environment.set('refresh', r.data.refresh);",
                  "}"
                ],
                "type": "text/javascript"
              }
            }
          ]
        },
        {
          "name": "Social Login / Registration",
          "request": {
            "method": "POST",
            "header": [
              {
                "key": "Content-Type",
                "value": "application/json",
                "type": "text"
              }
            ],
            "url": {
              "raw": "{{base_url}}/api/auth/social-auth/",
              "host": [
                "{{base_url}}"
              ],
              "path": [
                "api",
                "auth",
                "social-auth",
                ""
              ]
            },
            "body": {
              "mode": "raw",
              "raw": "{\n  \"email\": \"socialuser@test.com\",\n  \"provider\": \"google\",\n  \"name\": \"Social User\"\n}",
              "options": {
                "raw": {
                  "language": "json"
                }
              }
            }
          },
          "response": []
        },
        {
          "name": "Refresh Token",
          "request": {
            "method": "POST",
            "header": [
              {
                "key": "Content-Type",
                "value": "application/json",
                "type": "text"
              }
            ],
            "url": {
              "raw": "{{base_url}}/api/auth/token/refresh/",
              "host": [
                "{{base_url}}"
              ],
              "path": [
                "api",
                "auth",
                "token",
                "refresh",
                ""
              ]
            },
            "body": {
              "mode": "raw",
              "raw": "{\n  \"refresh\": \"{{refresh}}\"\n}",
              "options": {
                "raw": {
                  "language": "json"
                }
              }
            }
          },
          "response": []
        },
        {
          "name": "Get Me",
          "request": {
            "method": "GET",
            "header": [
              {
                "key": "Authorization",
                "value": "Bearer {{access}}",
                "type": "text"
              }
            ],
            "url": {
              "raw": "{{base_url}}/api/auth/me/",
              "host": [
                "{{base_url}}"
              ],
              "path": [
                "api",
                "auth",
                "me",
                ""
              ]
            }
          },
          "response": []
        },
        {
          "name": "Update Me",
          "request": {
            "method": "PATCH",
            "header": [
              {
                "key": "Authorization",
                "value": "Bearer {{access}}",
                "type": "text"
              },
              {
                "key": "Content-Type",
                "value": "application/json",
                "type": "text"
              }
            ],
            "url": {
              "raw": "{{base_url}}/api/auth/me/",
              "host": [
                "{{base_url}}"
              ],
              "path": [
                "api",
                "auth",
                "me",
                ""
              ]
            },
            "body": {
              "mode": "raw",
              "raw": "{\n  \"full_name\": \"Johal Al-Rashid\"\n}",
              "options": {
                "raw": {
                  "language": "json"
                }
              }
            }
          },
          "response": []
        },
        {
          "name": "Get User Profile",
          "request": {
            "method": "GET",
            "header": [
              {
                "key": "Authorization",
                "value": "Bearer {{access}}",
                "type": "text"
              }
            ],
            "url": {
              "raw": "{{base_url}}/api/auth/profile/",
              "host": [
                "{{base_url}}"
              ],
              "path": [
                "api",
                "auth",
                "profile",
                ""
              ]
            }
          },
          "response": []
        },
        {
          "name": "Update User Profile (Full)",
          "request": {
            "method": "PUT",
            "header": [
              {
                "key": "Authorization",
                "value": "Bearer {{access}}",
                "type": "text"
              },
              {
                "key": "Content-Type",
                "value": "application/json",
                "type": "text"
              }
            ],
            "url": {
              "raw": "{{base_url}}/api/auth/profile/",
              "host": [
                "{{base_url}}"
              ],
              "path": [
                "api",
                "auth",
                "profile",
                ""
              ]
            },
            "body": {
              "mode": "raw",
              "raw": "{\n  \"name\": \"Johal Store\",\n  \"phone\": \"+447700123456\",\n  \"bio\": \"Expert electronics retailer since 2010\"\n}",
              "options": {
                "raw": {
                  "language": "json"
                }
              }
            }
          },
          "response": []
        },
        {
          "name": "Update Profile Details (Email/Bio)",
          "request": {
            "method": "PATCH",
            "header": [
              {
                "key": "Authorization",
                "value": "Bearer {{access}}",
                "type": "text"
              },
              {
                "key": "Content-Type",
                "value": "application/json",
                "type": "text"
              }
            ],
            "url": {
              "raw": "{{base_url}}/api/auth/profile/update/",
              "host": [
                "{{base_url}}"
              ],
              "path": [
                "api",
                "auth",
                "profile",
                "update",
                ""
              ]
            },
            "body": {
              "mode": "raw",
              "raw": "{\n  \"name\": \"Johal Store Updated\",\n  \"email\": \"newemail@johal.com\",\n  \"phone\": \"+447700987654\",\n  \"bio\": \"New bio description\",\n  \"date_of_birth\": \"1995-01-01\",\n  \"gender\": \"male\"\n}",
              "options": {
                "raw": {
                  "language": "json"
                }
              }
            }
          },
          "response": []
        },
        {
          "name": "Verify Profile Email Change",
          "request": {
            "method": "POST",
            "header": [
              {
                "key": "Authorization",
                "value": "Bearer {{access}}",
                "type": "text"
              },
              {
                "key": "Content-Type",
                "value": "application/json",
                "type": "text"
              }
            ],
            "url": {
              "raw": "{{base_url}}/api/auth/profile/verify-email-change/",
              "host": [
                "{{base_url}}"
              ],
              "path": [
                "api",
                "auth",
                "profile",
                "verify-email-change",
                ""
              ]
            },
            "body": {
              "mode": "raw",
              "raw": "{\n  \"otp\": \"1234\"\n}",
              "options": {
                "raw": {
                  "language": "json"
                }
              }
            }
          },
          "response": []
        },
        {
          "name": "Get Tenant",
          "request": {
            "method": "GET",
            "header": [
              {
                "key": "Authorization",
                "value": "Bearer {{access}}",
                "type": "text"
              }
            ],
            "url": {
              "raw": "{{base_url}}/api/auth/tenant/",
              "host": [
                "{{base_url}}"
              ],
              "path": [
                "api",
                "auth",
                "tenant",
                ""
              ]
            }
          },
          "response": []
        },
        {
          "name": "Update Tenant",
          "request": {
            "method": "PATCH",
            "header": [
              {
                "key": "Authorization",
                "value": "Bearer {{access}}",
                "type": "text"
              },
              {
                "key": "Content-Type",
                "value": "application/json",
                "type": "text"
              }
            ],
            "url": {
              "raw": "{{base_url}}/api/auth/tenant/",
              "host": [
                "{{base_url}}"
              ],
              "path": [
                "api",
                "auth",
                "tenant",
                ""
              ]
            },
            "body": {
              "mode": "raw",
              "raw": "{\n  \"name\": \"Johal Electronics\"\n}",
              "options": {
                "raw": {
                  "language": "json"
                }
              }
            }
          },
          "response": []
        },
        {
          "name": "Invite Agent",
          "request": {
            "method": "POST",
            "header": [
              {
                "key": "Authorization",
                "value": "Bearer {{access}}",
                "type": "text"
              },
              {
                "key": "Content-Type",
                "value": "application/json",
                "type": "text"
              }
            ],
            "url": {
              "raw": "{{base_url}}/api/auth/agents/",
              "host": [
                "{{base_url}}"
              ],
              "path": [
                "api",
                "auth",
                "agents",
                ""
              ]
            },
            "body": {
              "mode": "raw",
              "raw": "{\n  \"email\": \"agent@johal.com\",\n  \"full_name\": \"Support Agent\",\n  \"password\": \"AgentPass123!\"\n}",
              "options": {
                "raw": {
                  "language": "json"
                }
              }
            }
          },
          "response": []
        },
        {
          "name": "List Agents",
          "request": {
            "method": "GET",
            "header": [
              {
                "key": "Authorization",
                "value": "Bearer {{access}}",
                "type": "text"
              }
            ],
            "url": {
              "raw": "{{base_url}}/api/auth/agents/",
              "host": [
                "{{base_url}}"
              ],
              "path": [
                "api",
                "auth",
                "agents",
                ""
              ]
            }
          },
          "response": []
        },
        {
          "name": "Change Password",
          "request": {
            "method": "POST",
            "header": [
              {
                "key": "Authorization",
                "value": "Bearer {{access}}",
                "type": "text"
              },
              {
                "key": "Content-Type",
                "value": "application/json",
                "type": "text"
              }
            ],
            "url": {
              "raw": "{{base_url}}/api/auth/password/change/",
              "host": [
                "{{base_url}}"
              ],
              "path": [
                "api",
                "auth",
                "password",
                "change",
                ""
              ]
            },
            "body": {
              "mode": "raw",
              "raw": "{\n  \"old_password\": \"StrongPass123!\",\n  \"new_password\": \"NewPass456!\",\n  \"new_password2\": \"NewPass456!\"\n}",
              "options": {
                "raw": {
                  "language": "json"
                }
              }
            }
          },
          "response": []
        },
        {
          "name": "Logout",
          "request": {
            "method": "POST",
            "header": [
              {
                "key": "Authorization",
                "value": "Bearer {{access}}",
                "type": "text"
              },
              {
                "key": "Content-Type",
                "value": "application/json",
                "type": "text"
              }
            ],
            "url": {
              "raw": "{{base_url}}/api/auth/logout/",
              "host": [
                "{{base_url}}"
              ],
              "path": [
                "api",
                "auth",
                "logout",
                ""
              ]
            },
            "body": {
              "mode": "raw",
              "raw": "{\n  \"refresh\": \"{{refresh}}\"\n}",
              "options": {
                "raw": {
                  "language": "json"
                }
              }
            }
          },
          "response": []
        },
        {
          "name": "Resend OTP",
          "request": {
            "method": "POST",
            "header": [
              {
                "key": "Content-Type",
                "value": "application/json",
                "type": "text"
              }
            ],
            "url": {
              "raw": "{{base_url}}/api/auth/resend-otp/",
              "host": [
                "{{base_url}}"
              ],
              "path": [
                "api",
                "auth",
                "resend-otp",
                ""
              ]
            },
            "body": {
              "mode": "raw",
              "raw": "{\n  \"email\": \"johal@test.com\",\n  \"purpose\": \"verification\"\n}",
              "options": {
                "raw": {
                  "language": "json"
                }
              }
            }
          },
          "response": []
        },
        {
          "name": "Reset Password Request",
          "request": {
            "method": "POST",
            "header": [
              {
                "key": "Content-Type",
                "value": "application/json",
                "type": "text"
              }
            ],
            "url": {
              "raw": "{{base_url}}/api/auth/password/reset-request/",
              "host": [
                "{{base_url}}"
              ],
              "path": [
                "api",
                "auth",
                "password",
                "reset-request",
                ""
              ]
            },
            "body": {
              "mode": "raw",
              "raw": "{\n  \"email\": \"johal@test.com\"\n}",
              "options": {
                "raw": {
                  "language": "json"
                }
              }
            }
          },
          "response": []
        },
        {
          "name": "Reset Password Verify OTP",
          "request": {
            "method": "POST",
            "header": [
              {
                "key": "Content-Type",
                "value": "application/json",
                "type": "text"
              }
            ],
            "url": {
              "raw": "{{base_url}}/api/auth/password/reset-verify-otp/",
              "host": [
                "{{base_url}}"
              ],
              "path": [
                "api",
                "auth",
                "password",
                "reset-verify-otp",
                ""
              ]
            },
            "body": {
              "mode": "raw",
              "raw": "{\n  \"email\": \"johal@test.com\",\n  \"otp\": \"1234\"\n}",
              "options": {
                "raw": {
                  "language": "json"
                }
              }
            }
          },
          "response": []
        },
        {
          "name": "Reset Password Confirm",
          "request": {
            "method": "POST",
            "header": [
              {
                "key": "Content-Type",
                "value": "application/json",
                "type": "text"
              }
            ],
            "url": {
              "raw": "{{base_url}}/api/auth/password/reset-confirm/",
              "host": [
                "{{base_url}}"
              ],
              "path": [
                "api",
                "auth",
                "password",
                "reset-confirm",
                ""
              ]
            },
            "body": {
              "mode": "raw",
              "raw": "{\n  \"email\": \"johal@test.com\",\n  \"otp\": \"1234\",\n  \"new_password\": \"NewPass456!\",\n  \"new_password2\": \"NewPass456!\"\n}",
              "options": {
                "raw": {
                  "language": "json"
                }
              }
            }
          },
          "response": []
        },
        {
          "name": "Soft Delete Account",
          "request": {
            "method": "POST",
            "header": [
              {
                "key": "Authorization",
                "value": "Bearer {{access}}",
                "type": "text"
              },
              {
                "key": "Content-Type",
                "value": "application/json",
                "type": "text"
              }
            ],
            "url": {
              "raw": "{{base_url}}/api/auth/account/delete/",
              "host": [
                "{{base_url}}"
              ],
              "path": [
                "api",
                "auth",
                "account",
                "delete",
                ""
              ]
            },
            "body": {
              "mode": "raw",
              "raw": "{\n  \"confirm\": true\n}",
              "options": {
                "raw": {
                  "language": "json"
                }
              }
            }
          },
          "response": []
        },
        {
          "name": "Restore Account (Admin Only)",
          "request": {
            "method": "POST",
            "header": [
              {
                "key": "Authorization",
                "value": "Bearer {{access}}",
                "type": "text"
              },
              {
                "key": "Content-Type",
                "value": "application/json",
                "type": "text"
              }
            ],
            "url": {
              "raw": "{{base_url}}/api/auth/account/restore/",
              "host": [
                "{{base_url}}"
              ],
              "path": [
                "api",
                "auth",
                "account",
                "restore",
                ""
              ]
            },
            "body": {
              "mode": "raw",
              "raw": "{\n  \"email\": \"johal@test.com\"\n}",
              "options": {
                "raw": {
                  "language": "json"
                }
              }
            }
          },
          "response": []
        }
      ]
    },
    {
      "name": "2 - Bots",
      "item": [
        {
          "name": "Create Bot",
          "request": {
            "method": "POST",
            "header": [
              {
                "key": "Authorization",
                "value": "Bearer {{access}}",
                "type": "text"
              }
            ],
            "url": {
              "raw": "{{base_url}}/api/bots/",
              "host": [
                "{{base_url}}"
              ],
              "path": [
                "api",
                "bots",
                ""
              ]
            },
            "body": {
              "mode": "formdata",
              "formdata": [
                {
                  "key": "name",
                  "value": "Johal AI Assistant",
                  "type": "text"
                },
                {
                  "key": "business_context",
                  "value": "We sell electronics in London. Free shipping over \u00a350. Returns: 30 days.",
                  "type": "text"
                },
                {
                  "key": "widget_enabled",
                  "value": "true",
                  "type": "text"
                },
                {
                  "key": "website_url",
                  "value": "https://en.wikipedia.org/wiki/Artificial_intelligence",
                  "type": "text"
                },
                {
                  "key": "files",
                  "type": "file",
                  "src": ""
                }
              ]
            }
          },
          "response": [],
          "event": [
            {
              "listen": "test",
              "script": {
                "exec": [
                  "const r = pm.response.json();",
                  "if(r.id) pm.environment.set('bot_id', r.id);",
                  "else if(r.data && r.data.id) pm.environment.set('bot_id', r.data.id);"
                ],
                "type": "text/javascript"
              }
            }
          ]
        },
        {
          "name": "List Bots",
          "request": {
            "method": "GET",
            "header": [
              {
                "key": "Authorization",
                "value": "Bearer {{access}}",
                "type": "text"
              }
            ],
            "url": {
              "raw": "{{base_url}}/api/bots/",
              "host": [
                "{{base_url}}"
              ],
              "path": [
                "api",
                "bots",
                ""
              ]
            }
          },
          "response": []
        },
        {
          "name": "Get Bot",
          "request": {
            "method": "GET",
            "header": [
              {
                "key": "Authorization",
                "value": "Bearer {{access}}",
                "type": "text"
              }
            ],
            "url": {
              "raw": "{{base_url}}/api/bots/{{bot_id}}/",
              "host": [
                "{{base_url}}"
              ],
              "path": [
                "api",
                "bots",
                "{{bot_id}}",
                ""
              ]
            }
          },
          "response": []
        },
        {
          "name": "Update Bot",
          "request": {
            "method": "PATCH",
            "header": [
              {
                "key": "Authorization",
                "value": "Bearer {{access}}",
                "type": "text"
              }
            ],
            "url": {
              "raw": "{{base_url}}/api/bots/{{bot_id}}/",
              "host": [
                "{{base_url}}"
              ],
              "path": [
                "api",
                "bots",
                "{{bot_id}}",
                ""
              ]
            },
            "body": {
              "mode": "formdata",
              "formdata": [
                {
                  "key": "name",
                  "value": "Johal Store Bot",
                  "type": "text"
                },
                {
                  "key": "business_context",
                  "value": "Johal Electronics - London's top electronics retailer since 2010.",
                  "type": "text"
                },
                {
                  "key": "widget_enabled",
                  "value": "true",
                  "type": "text"
                },
                {
                  "key": "website_url",
                  "value": "https://en.wikipedia.org/wiki/Artificial_intelligence",
                  "type": "text"
                },
                {
                  "key": "files",
                  "type": "file",
                  "src": ""
                }
              ]
            }
          },
          "response": []
        },
        {
          "name": "Get Design",
          "request": {
            "method": "GET",
            "header": [
              {
                "key": "Authorization",
                "value": "Bearer {{access}}",
                "type": "text"
              }
            ],
            "url": {
              "raw": "{{base_url}}/api/bots/{{bot_id}}/design/",
              "host": [
                "{{base_url}}"
              ],
              "path": [
                "api",
                "bots",
                "{{bot_id}}",
                "design",
                ""
              ]
            }
          },
          "response": []
        },
        {
          "name": "Update Design",
          "request": {
            "method": "PATCH",
            "header": [
              {
                "key": "Authorization",
                "value": "Bearer {{access}}",
                "type": "text"
              },
              {
                "key": "Content-Type",
                "value": "application/json",
                "type": "text"
              }
            ],
            "url": {
              "raw": "{{base_url}}/api/bots/{{bot_id}}/design/",
              "host": [
                "{{base_url}}"
              ],
              "path": [
                "api",
                "bots",
                "{{bot_id}}",
                "design",
                ""
              ]
            },
            "body": {
              "mode": "raw",
              "raw": "{\n  \"header_text\": \"Chat with Johal\",\n  \"welcome_message\": \"Hi! How can I help you today?\",\n  \"theme_color\": \"#7C3AED\",\n  \"font_family\": \"Inter\",\n  \"widget_position\": \"right\",\n  \"widget_size\": \"medium\",\n  \"border_radius\": 16,\n  \"predefined_questions\": [\n    \"What products do you sell?\",\n    \"Do you ship internationally?\",\n    \"What is your return policy?\"\n  ],\n  \"enable_pulsing\": true,\n  \"remove_branding\": false\n}",
              "options": {
                "raw": {
                  "language": "json"
                }
              }
            }
          },
          "response": []
        },
        {
          "name": "Add Behavior 1",
          "request": {
            "method": "POST",
            "header": [
              {
                "key": "Authorization",
                "value": "Bearer {{access}}",
                "type": "text"
              },
              {
                "key": "Content-Type",
                "value": "application/json",
                "type": "text"
              }
            ],
            "url": {
              "raw": "{{base_url}}/api/bots/{{bot_id}}/behaviors/",
              "host": [
                "{{base_url}}"
              ],
              "path": [
                "api",
                "bots",
                "{{bot_id}}",
                "behaviors",
                ""
              ]
            },
            "body": {
              "mode": "raw",
              "raw": "{\n  \"instruction\": \"Always greet warmly and end with: Is there anything else I can help you with?\",\n  \"order\": 1\n}",
              "options": {
                "raw": {
                  "language": "json"
                }
              }
            }
          },
          "response": [],
          "event": [
            {
              "listen": "test",
              "script": {
                "exec": [
                  "const r = pm.response.json();",
                  "if(r.id) pm.environment.set('behavior_id', r.id);",
                  "else if(r.data && r.data.id) pm.environment.set('behavior_id', r.data.id);"
                ],
                "type": "text/javascript"
              }
            }
          ]
        },
        {
          "name": "Add Behavior 2",
          "request": {
            "method": "POST",
            "header": [
              {
                "key": "Authorization",
                "value": "Bearer {{access}}",
                "type": "text"
              },
              {
                "key": "Content-Type",
                "value": "application/json",
                "type": "text"
              }
            ],
            "url": {
              "raw": "{{base_url}}/api/bots/{{bot_id}}/behaviors/",
              "host": [
                "{{base_url}}"
              ],
              "path": [
                "api",
                "bots",
                "{{bot_id}}",
                "behaviors",
                ""
              ]
            },
            "body": {
              "mode": "raw",
              "raw": "{\n  \"instruction\": \"Never mention competitor stores. Redirect to our catalogue.\",\n  \"order\": 2\n}",
              "options": {
                "raw": {
                  "language": "json"
                }
              }
            }
          },
          "response": []
        },
        {
          "name": "List Behaviors",
          "request": {
            "method": "GET",
            "header": [
              {
                "key": "Authorization",
                "value": "Bearer {{access}}",
                "type": "text"
              }
            ],
            "url": {
              "raw": "{{base_url}}/api/bots/{{bot_id}}/behaviors/",
              "host": [
                "{{base_url}}"
              ],
              "path": [
                "api",
                "bots",
                "{{bot_id}}",
                "behaviors",
                ""
              ]
            }
          },
          "response": []
        },
        {
          "name": "Update Behavior",
          "request": {
            "method": "PATCH",
            "header": [
              {
                "key": "Authorization",
                "value": "Bearer {{access}}",
                "type": "text"
              },
              {
                "key": "Content-Type",
                "value": "application/json",
                "type": "text"
              }
            ],
            "url": {
              "raw": "{{base_url}}/api/bots/{{bot_id}}/behaviors/{{behavior_id}}/",
              "host": [
                "{{base_url}}"
              ],
              "path": [
                "api",
                "bots",
                "{{bot_id}}",
                "behaviors",
                "{{behavior_id}}",
                ""
              ]
            },
            "body": {
              "mode": "raw",
              "raw": "{\n  \"instruction\": \"Always be professional. End with a helpful question.\"\n}",
              "options": {
                "raw": {
                  "language": "json"
                }
              }
            }
          },
          "response": []
        },
        {
          "name": "Delete Behavior",
          "request": {
            "method": "DELETE",
            "header": [
              {
                "key": "Authorization",
                "value": "Bearer {{access}}",
                "type": "text"
              }
            ],
            "url": {
              "raw": "{{base_url}}/api/bots/{{bot_id}}/behaviors/{{behavior_id}}/",
              "host": [
                "{{base_url}}"
              ],
              "path": [
                "api",
                "bots",
                "{{bot_id}}",
                "behaviors",
                "{{behavior_id}}",
                ""
              ]
            }
          },
          "response": []
        },
        {
          "name": "Public Bot Config (NO AUTH)",
          "request": {
            "method": "GET",
            "header": [],
            "url": {
              "raw": "{{base_url}}/api/bots/public/{{bot_id}}/config/",
              "host": [
                "{{base_url}}"
              ],
              "path": [
                "api",
                "bots",
                "public",
                "{{bot_id}}",
                "config",
                ""
              ]
            }
          },
          "response": []
        },
        {
          "name": "Delete Bot",
          "request": {
            "method": "DELETE",
            "header": [
              {
                "key": "Authorization",
                "value": "Bearer {{access}}",
                "type": "text"
              }
            ],
            "url": {
              "raw": "{{base_url}}/api/bots/{{bot_id}}/",
              "host": [
                "{{base_url}}"
              ],
              "path": [
                "api",
                "bots",
                "{{bot_id}}",
                ""
              ]
            }
          },
          "response": []
        }
      ]
    },
    {
      "name": "3 - Knowledge Base",
      "item": [
        {
          "name": "3a - Websites",
          "item": [
            {
              "name": "Add Website",
              "request": {
                "method": "POST",
                "header": [
                  {
                    "key": "Authorization",
                    "value": "Bearer {{access}}",
                    "type": "text"
                  },
                  {
                    "key": "Content-Type",
                    "value": "application/json",
                    "type": "text"
                  }
                ],
                "url": {
                  "raw": "{{base_url}}/api/knowledge/{{bot_id}}/websites/",
                  "host": [
                    "{{base_url}}"
                  ],
                  "path": [
                    "api",
                    "knowledge",
                    "{{bot_id}}",
                    "websites",
                    ""
                  ]
                },
                "body": {
                  "mode": "raw",
                  "raw": "{\n  \"url\": \"https://en.wikipedia.org/wiki/Artificial_intelligence\",\n  \"auto_rescrape\": false\n}",
                  "options": {
                    "raw": {
                      "language": "json"
                    }
                  }
                }
              },
              "response": [],
              "event": [
                {
                  "listen": "test",
                  "script": {
                    "exec": [
                      "const r = pm.response.json();",
                      "if(r.id) pm.environment.set('source_id', r.id);",
                      "else if(r.data && r.data.id) pm.environment.set('source_id', r.data.id);"
                    ],
                    "type": "text/javascript"
                  }
                }
              ]
            },
            {
              "name": "List Websites",
              "request": {
                "method": "GET",
                "header": [
                  {
                    "key": "Authorization",
                    "value": "Bearer {{access}}",
                    "type": "text"
                  }
                ],
                "url": {
                  "raw": "{{base_url}}/api/knowledge/{{bot_id}}/websites/",
                  "host": [
                    "{{base_url}}"
                  ],
                  "path": [
                    "api",
                    "knowledge",
                    "{{bot_id}}",
                    "websites",
                    ""
                  ]
                }
              },
              "response": []
            },
            {
              "name": "Get Website",
              "request": {
                "method": "GET",
                "header": [
                  {
                    "key": "Authorization",
                    "value": "Bearer {{access}}",
                    "type": "text"
                  }
                ],
                "url": {
                  "raw": "{{base_url}}/api/knowledge/{{bot_id}}/websites/{{source_id}}/",
                  "host": [
                    "{{base_url}}"
                  ],
                  "path": [
                    "api",
                    "knowledge",
                    "{{bot_id}}",
                    "websites",
                    "{{source_id}}",
                    ""
                  ]
                }
              },
              "response": []
            },
            {
              "name": "Rescrape Website",
              "request": {
                "method": "POST",
                "header": [
                  {
                    "key": "Authorization",
                    "value": "Bearer {{access}}",
                    "type": "text"
                  }
                ],
                "url": {
                  "raw": "{{base_url}}/api/knowledge/{{bot_id}}/websites/{{source_id}}/rescrape/",
                  "host": [
                    "{{base_url}}"
                  ],
                  "path": [
                    "api",
                    "knowledge",
                    "{{bot_id}}",
                    "websites",
                    "{{source_id}}",
                    "rescrape",
                    ""
                  ]
                }
              },
              "response": []
            },
            {
              "name": "Toggle Auto-Rescrape",
              "request": {
                "method": "PATCH",
                "header": [
                  {
                    "key": "Authorization",
                    "value": "Bearer {{access}}",
                    "type": "text"
                  },
                  {
                    "key": "Content-Type",
                    "value": "application/json",
                    "type": "text"
                  }
                ],
                "url": {
                  "raw": "{{base_url}}/api/knowledge/{{bot_id}}/websites/{{source_id}}/",
                  "host": [
                    "{{base_url}}"
                  ],
                  "path": [
                    "api",
                    "knowledge",
                    "{{bot_id}}",
                    "websites",
                    "{{source_id}}",
                    ""
                  ]
                },
                "body": {
                  "mode": "raw",
                  "raw": "{\n  \"auto_rescrape\": true\n}",
                  "options": {
                    "raw": {
                      "language": "json"
                    }
                  }
                }
              },
              "response": []
            },
            {
              "name": "Delete Website",
              "request": {
                "method": "DELETE",
                "header": [
                  {
                    "key": "Authorization",
                    "value": "Bearer {{access}}",
                    "type": "text"
                  }
                ],
                "url": {
                  "raw": "{{base_url}}/api/knowledge/{{bot_id}}/websites/{{source_id}}/",
                  "host": [
                    "{{base_url}}"
                  ],
                  "path": [
                    "api",
                    "knowledge",
                    "{{bot_id}}",
                    "websites",
                    "{{source_id}}",
                    ""
                  ]
                }
              },
              "response": []
            }
          ]
        },
        {
          "name": "3b - File Uploads",
          "item": [
            {
              "name": "Upload File (multipart)",
              "request": {
                "method": "POST",
                "header": [
                  {
                    "key": "Authorization",
                    "value": "Bearer {{access}}",
                    "type": "text"
                  }
                ],
                "url": {
                  "raw": "{{base_url}}/api/knowledge/{{bot_id}}/files/",
                  "host": [
                    "{{base_url}}"
                  ],
                  "path": [
                    "api",
                    "knowledge",
                    "{{bot_id}}",
                    "files",
                    ""
                  ]
                },
                "body": {
                  "mode": "formdata",
                  "formdata": [
                    {
                      "key": "file",
                      "type": "file",
                      "src": ""
                    }
                  ]
                }
              },
              "response": []
            },
            {
              "name": "List Files",
              "request": {
                "method": "GET",
                "header": [
                  {
                    "key": "Authorization",
                    "value": "Bearer {{access}}",
                    "type": "text"
                  }
                ],
                "url": {
                  "raw": "{{base_url}}/api/knowledge/{{bot_id}}/files/",
                  "host": [
                    "{{base_url}}"
                  ],
                  "path": [
                    "api",
                    "knowledge",
                    "{{bot_id}}",
                    "files",
                    ""
                  ]
                }
              },
              "response": []
            }
          ]
        },
        {
          "name": "3c - Q&A Pairs",
          "item": [
            {
              "name": "Add Q&A 1",
              "request": {
                "method": "POST",
                "header": [
                  {
                    "key": "Authorization",
                    "value": "Bearer {{access}}",
                    "type": "text"
                  },
                  {
                    "key": "Content-Type",
                    "value": "application/json",
                    "type": "text"
                  }
                ],
                "url": {
                  "raw": "{{base_url}}/api/knowledge/{{bot_id}}/qa/",
                  "host": [
                    "{{base_url}}"
                  ],
                  "path": [
                    "api",
                    "knowledge",
                    "{{bot_id}}",
                    "qa",
                    ""
                  ]
                },
                "body": {
                  "mode": "raw",
                  "raw": "{\n  \"question\": \"What is your return policy?\",\n  \"answer\": \"30 days, unused, original packaging. Email support@johal.com.\"\n}",
                  "options": {
                    "raw": {
                      "language": "json"
                    }
                  }
                }
              },
              "response": []
            },
            {
              "name": "Add Q&A 2",
              "request": {
                "method": "POST",
                "header": [
                  {
                    "key": "Authorization",
                    "value": "Bearer {{access}}",
                    "type": "text"
                  },
                  {
                    "key": "Content-Type",
                    "value": "application/json",
                    "type": "text"
                  }
                ],
                "url": {
                  "raw": "{{base_url}}/api/knowledge/{{bot_id}}/qa/",
                  "host": [
                    "{{base_url}}"
                  ],
                  "path": [
                    "api",
                    "knowledge",
                    "{{bot_id}}",
                    "qa",
                    ""
                  ]
                },
                "body": {
                  "mode": "raw",
                  "raw": "{\n  \"question\": \"Do you ship internationally?\",\n  \"answer\": \"Yes, 50+ countries. UK 2-3 days, International 5-7 days.\"\n}",
                  "options": {
                    "raw": {
                      "language": "json"
                    }
                  }
                }
              },
              "response": []
            },
            {
              "name": "Add Q&A 3",
              "request": {
                "method": "POST",
                "header": [
                  {
                    "key": "Authorization",
                    "value": "Bearer {{access}}",
                    "type": "text"
                  },
                  {
                    "key": "Content-Type",
                    "value": "application/json",
                    "type": "text"
                  }
                ],
                "url": {
                  "raw": "{{base_url}}/api/knowledge/{{bot_id}}/qa/",
                  "host": [
                    "{{base_url}}"
                  ],
                  "path": [
                    "api",
                    "knowledge",
                    "{{bot_id}}",
                    "qa",
                    ""
                  ]
                },
                "body": {
                  "mode": "raw",
                  "raw": "{\n  \"question\": \"What are your opening hours?\",\n  \"answer\": \"Mon-Fri 9am-6pm, Sat 10am-4pm, closed Sunday.\"\n}",
                  "options": {
                    "raw": {
                      "language": "json"
                    }
                  }
                }
              },
              "response": []
            },
            {
              "name": "List Q&A",
              "request": {
                "method": "GET",
                "header": [
                  {
                    "key": "Authorization",
                    "value": "Bearer {{access}}",
                    "type": "text"
                  }
                ],
                "url": {
                  "raw": "{{base_url}}/api/knowledge/{{bot_id}}/qa/",
                  "host": [
                    "{{base_url}}"
                  ],
                  "path": [
                    "api",
                    "knowledge",
                    "{{bot_id}}",
                    "qa",
                    ""
                  ]
                }
              },
              "response": []
            },
            {
              "name": "Update Q&A",
              "request": {
                "method": "PATCH",
                "header": [
                  {
                    "key": "Authorization",
                    "value": "Bearer {{access}}",
                    "type": "text"
                  },
                  {
                    "key": "Content-Type",
                    "value": "application/json",
                    "type": "text"
                  }
                ],
                "url": {
                  "raw": "{{base_url}}/api/knowledge/{{bot_id}}/qa/REPLACE_QA_ID/",
                  "host": [
                    "{{base_url}}"
                  ],
                  "path": [
                    "api",
                    "knowledge",
                    "{{bot_id}}",
                    "qa",
                    "REPLACE_QA_ID",
                    ""
                  ]
                },
                "body": {
                  "mode": "raw",
                  "raw": "{\n  \"answer\": \"Updated: 45 days return policy now.\"\n}",
                  "options": {
                    "raw": {
                      "language": "json"
                    }
                  }
                }
              },
              "response": []
            },
            {
              "name": "Delete Q&A",
              "request": {
                "method": "DELETE",
                "header": [
                  {
                    "key": "Authorization",
                    "value": "Bearer {{access}}",
                    "type": "text"
                  }
                ],
                "url": {
                  "raw": "{{base_url}}/api/knowledge/{{bot_id}}/qa/REPLACE_QA_ID/",
                  "host": [
                    "{{base_url}}"
                  ],
                  "path": [
                    "api",
                    "knowledge",
                    "{{bot_id}}",
                    "qa",
                    "REPLACE_QA_ID",
                    ""
                  ]
                }
              },
              "response": []
            }
          ]
        },
        {
          "name": "3d - External Sources",
          "item": [
            {
              "name": "Google Drive - Check Status",
              "request": {
                "method": "GET",
                "header": [
                  {
                    "key": "Authorization",
                    "value": "Bearer {{access}}",
                    "type": "text"
                  }
                ],
                "url": {
                  "raw": "{{base_url}}/api/knowledge/{{bot_id}}/gdrive/",
                  "host": [
                    "{{base_url}}"
                  ],
                  "path": [
                    "api",
                    "knowledge",
                    "{{bot_id}}",
                    "gdrive",
                    ""
                  ]
                }
              },
              "response": []
            },
            {
              "name": "Google Drive - Disconnect",
              "request": {
                "method": "DELETE",
                "header": [
                  {
                    "key": "Authorization",
                    "value": "Bearer {{access}}",
                    "type": "text"
                  }
                ],
                "url": {
                  "raw": "{{base_url}}/api/knowledge/{{bot_id}}/gdrive/",
                  "host": [
                    "{{base_url}}"
                  ],
                  "path": [
                    "api",
                    "knowledge",
                    "{{bot_id}}",
                    "gdrive",
                    ""
                  ]
                }
              },
              "response": []
            },
            {
              "name": "OneDrive - Check Status",
              "request": {
                "method": "GET",
                "header": [
                  {
                    "key": "Authorization",
                    "value": "Bearer {{access}}",
                    "type": "text"
                  }
                ],
                "url": {
                  "raw": "{{base_url}}/api/knowledge/{{bot_id}}/onedrive/",
                  "host": [
                    "{{base_url}}"
                  ],
                  "path": [
                    "api",
                    "knowledge",
                    "{{bot_id}}",
                    "onedrive",
                    ""
                  ]
                }
              },
              "response": []
            },
            {
              "name": "OneDrive - Disconnect",
              "request": {
                "method": "DELETE",
                "header": [
                  {
                    "key": "Authorization",
                    "value": "Bearer {{access}}",
                    "type": "text"
                  }
                ],
                "url": {
                  "raw": "{{base_url}}/api/knowledge/{{bot_id}}/onedrive/",
                  "host": [
                    "{{base_url}}"
                  ],
                  "path": [
                    "api",
                    "knowledge",
                    "{{bot_id}}",
                    "onedrive",
                    ""
                  ]
                }
              },
              "response": []
            },
            {
              "name": "Import External File",
              "request": {
                "method": "POST",
                "header": [
                  {
                    "key": "Authorization",
                    "value": "Bearer {{access}}",
                    "type": "text"
                  },
                  {
                    "key": "Content-Type",
                    "value": "application/json",
                    "type": "text"
                  }
                ],
                "url": {
                  "raw": "{{base_url}}/api/knowledge/{{bot_id}}/import-external/",
                  "host": [
                    "{{base_url}}"
                  ],
                  "path": [
                    "api",
                    "knowledge",
                    "{{bot_id}}",
                    "import-external",
                    ""
                  ]
                },
                "body": {
                  "mode": "raw",
                  "raw": "{\n  \"source_type\": \"google_drive\",\n  \"file_id\": \"file_12345\",\n  \"file_name\": \"Product_Catalog.pdf\"\n}",
                  "options": {
                    "raw": {
                      "language": "json"
                    }
                  }
                }
              },
              "response": []
            }
          ]
        }
      ]
    },
    {
      "name": "4 - Chat (NO AUTH - Widget)",
      "item": [
        {
          "name": "Chat - Hello",
          "request": {
            "method": "POST",
            "header": [
              {
                "key": "Content-Type",
                "value": "application/json",
                "type": "text"
              }
            ],
            "url": {
              "raw": "{{base_url}}/api/chat/",
              "host": [
                "{{base_url}}"
              ],
              "path": [
                "api",
                "chat",
                ""
              ]
            },
            "body": {
              "mode": "raw",
              "raw": "{\n  \"bot_id\": \"{{bot_id}}\",\n  \"session_id\": \"test_session_001\",\n  \"message\": \"Hello! What products do you sell?\"\n}",
              "options": {
                "raw": {
                  "language": "json"
                }
              }
            }
          },
          "response": []
        },
        {
          "name": "Chat - Test RAG",
          "request": {
            "method": "POST",
            "header": [
              {
                "key": "Content-Type",
                "value": "application/json",
                "type": "text"
              }
            ],
            "url": {
              "raw": "{{base_url}}/api/chat/",
              "host": [
                "{{base_url}}"
              ],
              "path": [
                "api",
                "chat",
                ""
              ]
            },
            "body": {
              "mode": "raw",
              "raw": "{\n  \"bot_id\": \"{{bot_id}}\",\n  \"session_id\": \"test_session_001\",\n  \"message\": \"What is your return policy?\"\n}",
              "options": {
                "raw": {
                  "language": "json"
                }
              }
            }
          },
          "response": []
        },
        {
          "name": "Chat - Trigger Lead Capture",
          "request": {
            "method": "POST",
            "header": [
              {
                "key": "Content-Type",
                "value": "application/json",
                "type": "text"
              }
            ],
            "url": {
              "raw": "{{base_url}}/api/chat/",
              "host": [
                "{{base_url}}"
              ],
              "path": [
                "api",
                "chat",
                ""
              ]
            },
            "body": {
              "mode": "raw",
              "raw": "{\n  \"bot_id\": \"{{bot_id}}\",\n  \"session_id\": \"test_session_001\",\n  \"message\": \"I want a quote for bulk order, can I leave my details?\"\n}",
              "options": {
                "raw": {
                  "language": "json"
                }
              }
            }
          },
          "response": []
        },
        {
          "name": "Chat - Provide Lead Details",
          "request": {
            "method": "POST",
            "header": [
              {
                "key": "Content-Type",
                "value": "application/json",
                "type": "text"
              }
            ],
            "url": {
              "raw": "{{base_url}}/api/chat/",
              "host": [
                "{{base_url}}"
              ],
              "path": [
                "api",
                "chat",
                ""
              ]
            },
            "body": {
              "mode": "raw",
              "raw": "{\n  \"bot_id\": \"{{bot_id}}\",\n  \"session_id\": \"test_session_001\",\n  \"message\": \"Ahmed, ahmed@test.com, +447700123456\"\n}",
              "options": {
                "raw": {
                  "language": "json"
                }
              }
            }
          },
          "response": []
        },
        {
          "name": "Chat - New Session",
          "request": {
            "method": "POST",
            "header": [
              {
                "key": "Content-Type",
                "value": "application/json",
                "type": "text"
              }
            ],
            "url": {
              "raw": "{{base_url}}/api/chat/",
              "host": [
                "{{base_url}}"
              ],
              "path": [
                "api",
                "chat",
                ""
              ]
            },
            "body": {
              "mode": "raw",
              "raw": "{\n  \"bot_id\": \"{{bot_id}}\",\n  \"session_id\": \"test_session_002\",\n  \"message\": \"Do you have iPhone 15 cases?\"\n}",
              "options": {
                "raw": {
                  "language": "json"
                }
              }
            }
          },
          "response": []
        }
      ]
    },
    {
      "name": "5 - Conversations",
      "item": [
        {
          "name": "WebSocket \u2014 Live updates socket",
          "request": {
            "method": "GET",
            "header": [
              {
                "key": "Authorization",
                "value": "Bearer {{access}}",
                "type": "text"
              }
            ],
            "url": {
              "raw": "ws://localhost:8000/ws/conversations/{{bot_id}}/",
              "protocol": "ws",
              "host": [
                "localhost"
              ],
              "port": "8000",
              "path": [
                "ws",
                "conversations",
                "{{bot_id}}",
                ""
              ]
            },
            "description": "Establish a WebSocket connection to listen to real-time conversation events for this bot (new conversations, new user/assistant messages, and conversation updates)."
          },
          "response": []
        },
        {
          "name": "List All Conversations",
          "request": {
            "method": "GET",
            "header": [
              {
                "key": "Authorization",
                "value": "Bearer {{access}}",
                "type": "text"
              }
            ],
            "url": {
              "raw": "{{base_url}}/api/conversations/",
              "host": [
                "{{base_url}}"
              ],
              "path": [
                "api",
                "conversations",
                ""
              ]
            }
          },
          "response": [],
          "event": [
            {
              "listen": "test",
              "script": {
                "exec": [
                  "const r = pm.response.json();",
                  "const items = Array.isArray(r) ? r : (r.results || r.data || []);",
                  "if(items.length > 0) pm.environment.set('conv_id', items[0].id);"
                ],
                "type": "text/javascript"
              }
            }
          ]
        },
        {
          "name": "Filter by Bot",
          "request": {
            "method": "GET",
            "header": [
              {
                "key": "Authorization",
                "value": "Bearer {{access}}",
                "type": "text"
              }
            ],
            "url": {
              "raw": "{{base_url}}/api/conversations/?bot={{bot_id}}",
              "host": [
                "{{base_url}}"
              ],
              "path": [
                "api",
                "conversations",
                "?bot={{bot_id}}"
              ]
            }
          },
          "response": []
        },
        {
          "name": "Filter by Channel",
          "request": {
            "method": "GET",
            "header": [
              {
                "key": "Authorization",
                "value": "Bearer {{access}}",
                "type": "text"
              }
            ],
            "url": {
              "raw": "{{base_url}}/api/conversations/?channel=website",
              "host": [
                "{{base_url}}"
              ],
              "path": [
                "api",
                "conversations",
                "?channel=website"
              ]
            }
          },
          "response": []
        },
        {
          "name": "Filter by Mode",
          "request": {
            "method": "GET",
            "header": [
              {
                "key": "Authorization",
                "value": "Bearer {{access}}",
                "type": "text"
              }
            ],
            "url": {
              "raw": "{{base_url}}/api/conversations/?mode=ai",
              "host": [
                "{{base_url}}"
              ],
              "path": [
                "api",
                "conversations",
                "?mode=ai"
              ]
            }
          },
          "response": []
        },
        {
          "name": "Search Conversations",
          "request": {
            "method": "GET",
            "header": [
              {
                "key": "Authorization",
                "value": "Bearer {{access}}",
                "type": "text"
              }
            ],
            "url": {
              "raw": "{{base_url}}/api/conversations/?search=Ahmed",
              "host": [
                "{{base_url}}"
              ],
              "path": [
                "api",
                "conversations",
                "?search=Ahmed"
              ]
            }
          },
          "response": []
        },
        {
          "name": "Get Conversation + Messages",
          "request": {
            "method": "GET",
            "header": [
              {
                "key": "Authorization",
                "value": "Bearer {{access}}",
                "type": "text"
              }
            ],
            "url": {
              "raw": "{{base_url}}/api/conversations/{{conv_id}}/",
              "host": [
                "{{base_url}}"
              ],
              "path": [
                "api",
                "conversations",
                "{{conv_id}}",
                ""
              ]
            }
          },
          "response": []
        },
        {
          "name": "Takeover (Human Mode)",
          "request": {
            "method": "POST",
            "header": [
              {
                "key": "Authorization",
                "value": "Bearer {{access}}",
                "type": "text"
              },
              {
                "key": "Content-Type",
                "value": "application/json",
                "type": "text"
              }
            ],
            "url": {
              "raw": "{{base_url}}/api/conversations/{{conv_id}}/handoff/",
              "host": [
                "{{base_url}}"
              ],
              "path": [
                "api",
                "conversations",
                "{{conv_id}}",
                "handoff",
                ""
              ]
            },
            "body": {
              "mode": "raw",
              "raw": "{\n  \"action\": \"takeover\"\n}",
              "options": {
                "raw": {
                  "language": "json"
                }
              }
            }
          },
          "response": []
        },
        {
          "name": "Send Agent Message",
          "request": {
            "method": "POST",
            "header": [
              {
                "key": "Authorization",
                "value": "Bearer {{access}}",
                "type": "text"
              },
              {
                "key": "Content-Type",
                "value": "application/json",
                "type": "text"
              }
            ],
            "url": {
              "raw": "{{base_url}}/api/conversations/{{conv_id}}/message/",
              "host": [
                "{{base_url}}"
              ],
              "path": [
                "api",
                "conversations",
                "{{conv_id}}",
                "message",
                ""
              ]
            },
            "body": {
              "mode": "raw",
              "raw": "{\n  \"content\": \"Hi Ahmed! Support team here. Checking stock for your bulk order now.\"\n}",
              "options": {
                "raw": {
                  "language": "json"
                }
              }
            }
          },
          "response": []
        },
        {
          "name": "Release (AI Mode)",
          "request": {
            "method": "POST",
            "header": [
              {
                "key": "Authorization",
                "value": "Bearer {{access}}",
                "type": "text"
              },
              {
                "key": "Content-Type",
                "value": "application/json",
                "type": "text"
              }
            ],
            "url": {
              "raw": "{{base_url}}/api/conversations/{{conv_id}}/handoff/",
              "host": [
                "{{base_url}}"
              ],
              "path": [
                "api",
                "conversations",
                "{{conv_id}}",
                "handoff",
                ""
              ]
            },
            "body": {
              "mode": "raw",
              "raw": "{\n  \"action\": \"release\"\n}",
              "options": {
                "raw": {
                  "language": "json"
                }
              }
            }
          },
          "response": []
        },
        {
          "name": "Delete Conversation",
          "request": {
            "method": "DELETE",
            "header": [
              {
                "key": "Authorization",
                "value": "Bearer {{access}}",
                "type": "text"
              }
            ],
            "url": {
              "raw": "{{base_url}}/api/conversations/{{conv_id}}/",
              "host": [
                "{{base_url}}"
              ],
              "path": [
                "api",
                "conversations",
                "{{conv_id}}",
                ""
              ]
            }
          },
          "response": []
        }
      ]
    },
    {
      "name": "6 - Leads",
      "item": [
        {
          "name": "List All Leads",
          "request": {
            "method": "GET",
            "header": [
              {
                "key": "Authorization",
                "value": "Bearer {{access}}",
                "type": "text"
              }
            ],
            "url": {
              "raw": "{{base_url}}/api/leads/",
              "host": [
                "{{base_url}}"
              ],
              "path": [
                "api",
                "leads",
                ""
              ]
            }
          },
          "response": [],
          "event": [
            {
              "listen": "test",
              "script": {
                "exec": [
                  "const r = pm.response.json();",
                  "const items = Array.isArray(r) ? r : (r.results || r.data || []);",
                  "if(items.length > 0) pm.environment.set('lead_id', items[0].id);"
                ],
                "type": "text/javascript"
              }
            }
          ]
        },
        {
          "name": "Filter by Bot",
          "request": {
            "method": "GET",
            "header": [
              {
                "key": "Authorization",
                "value": "Bearer {{access}}",
                "type": "text"
              }
            ],
            "url": {
              "raw": "{{base_url}}/api/leads/?bot={{bot_id}}",
              "host": [
                "{{base_url}}"
              ],
              "path": [
                "api",
                "leads",
                "?bot={{bot_id}}"
              ]
            }
          },
          "response": []
        },
        {
          "name": "Filter by Status",
          "request": {
            "method": "GET",
            "header": [
              {
                "key": "Authorization",
                "value": "Bearer {{access}}",
                "type": "text"
              }
            ],
            "url": {
              "raw": "{{base_url}}/api/leads/?status=new",
              "host": [
                "{{base_url}}"
              ],
              "path": [
                "api",
                "leads",
                "?status=new"
              ]
            }
          },
          "response": []
        },
        {
          "name": "Filter by Channel",
          "request": {
            "method": "GET",
            "header": [
              {
                "key": "Authorization",
                "value": "Bearer {{access}}",
                "type": "text"
              }
            ],
            "url": {
              "raw": "{{base_url}}/api/leads/?channel=website",
              "host": [
                "{{base_url}}"
              ],
              "path": [
                "api",
                "leads",
                "?channel=website"
              ]
            }
          },
          "response": []
        },
        {
          "name": "Search Leads",
          "request": {
            "method": "GET",
            "header": [
              {
                "key": "Authorization",
                "value": "Bearer {{access}}",
                "type": "text"
              }
            ],
            "url": {
              "raw": "{{base_url}}/api/leads/?search=Ahmed",
              "host": [
                "{{base_url}}"
              ],
              "path": [
                "api",
                "leads",
                "?search=Ahmed"
              ]
            }
          },
          "response": []
        },
        {
          "name": "Get Lead Detail",
          "request": {
            "method": "GET",
            "header": [
              {
                "key": "Authorization",
                "value": "Bearer {{access}}",
                "type": "text"
              }
            ],
            "url": {
              "raw": "{{base_url}}/api/leads/{{lead_id}}/",
              "host": [
                "{{base_url}}"
              ],
              "path": [
                "api",
                "leads",
                "{{lead_id}}",
                ""
              ]
            }
          },
          "response": []
        },
        {
          "name": "Update Lead - Contacted",
          "request": {
            "method": "PATCH",
            "header": [
              {
                "key": "Authorization",
                "value": "Bearer {{access}}",
                "type": "text"
              },
              {
                "key": "Content-Type",
                "value": "application/json",
                "type": "text"
              }
            ],
            "url": {
              "raw": "{{base_url}}/api/leads/{{lead_id}}/",
              "host": [
                "{{base_url}}"
              ],
              "path": [
                "api",
                "leads",
                "{{lead_id}}",
                ""
              ]
            },
            "body": {
              "mode": "raw",
              "raw": "{\n  \"status\": \"contacted\",\n  \"notes\": \"Called Ahmed. Very interested, sending quote.\"\n}",
              "options": {
                "raw": {
                  "language": "json"
                }
              }
            }
          },
          "response": []
        },
        {
          "name": "Update Lead - Converted",
          "request": {
            "method": "PATCH",
            "header": [
              {
                "key": "Authorization",
                "value": "Bearer {{access}}",
                "type": "text"
              },
              {
                "key": "Content-Type",
                "value": "application/json",
                "type": "text"
              }
            ],
            "url": {
              "raw": "{{base_url}}/api/leads/{{lead_id}}/",
              "host": [
                "{{base_url}}"
              ],
              "path": [
                "api",
                "leads",
                "{{lead_id}}",
                ""
              ]
            },
            "body": {
              "mode": "raw",
              "raw": "{\n  \"status\": \"converted\",\n  \"notes\": \"Order placed. 50 units confirmed.\"\n}",
              "options": {
                "raw": {
                  "language": "json"
                }
              }
            }
          },
          "response": []
        },
        {
          "name": "Export Leads CSV",
          "request": {
            "method": "GET",
            "header": [
              {
                "key": "Authorization",
                "value": "Bearer {{access}}",
                "type": "text"
              }
            ],
            "url": {
              "raw": "{{base_url}}/api/leads/export/?bot={{bot_id}}",
              "host": [
                "{{base_url}}"
              ],
              "path": [
                "api",
                "leads",
                "export",
                "?bot={{bot_id}}"
              ]
            }
          },
          "response": []
        }
      ]
    },
    {
      "name": "7 - Messaging",
      "item": [
        {
          "name": "7a - Connect Channels",
          "item": [
            {
              "name": "FB - Check Status",
              "request": {
                "method": "GET",
                "header": [
                  {
                    "key": "Authorization",
                    "value": "Bearer {{access}}",
                    "type": "text"
                  }
                ],
                "url": {
                  "raw": "{{base_url}}/api/messaging/facebook/?bot={{bot_id}}",
                  "host": [
                    "{{base_url}}"
                  ],
                  "path": [
                    "api",
                    "messaging",
                    "facebook",
                    "?bot={{bot_id}}"
                  ]
                }
              },
              "response": []
            },
            {
              "name": "FB - Connect",
              "request": {
                "method": "POST",
                "header": [
                  {
                    "key": "Authorization",
                    "value": "Bearer {{access}}",
                    "type": "text"
                  },
                  {
                    "key": "Content-Type",
                    "value": "application/json",
                    "type": "text"
                  }
                ],
                "url": {
                  "raw": "{{base_url}}/api/messaging/facebook/",
                  "host": [
                    "{{base_url}}"
                  ],
                  "path": [
                    "api",
                    "messaging",
                    "facebook",
                    ""
                  ]
                },
                "body": {
                  "mode": "raw",
                  "raw": "{\n  \"bot_id\": \"{{bot_id}}\",\n  \"page_id\": \"123456789\",\n  \"page_name\": \"Johal Store\",\n  \"page_access_token\": \"EAAxxxxxxxx\"\n}",
                  "options": {
                    "raw": {
                      "language": "json"
                    }
                  }
                }
              },
              "response": []
            },
            {
              "name": "FB - Disconnect",
              "request": {
                "method": "DELETE",
                "header": [
                  {
                    "key": "Authorization",
                    "value": "Bearer {{access}}",
                    "type": "text"
                  }
                ],
                "url": {
                  "raw": "{{base_url}}/api/messaging/facebook/?bot={{bot_id}}",
                  "host": [
                    "{{base_url}}"
                  ],
                  "path": [
                    "api",
                    "messaging",
                    "facebook",
                    "?bot={{bot_id}}"
                  ]
                }
              },
              "response": []
            },
            {
              "name": "WA - Check Status",
              "request": {
                "method": "GET",
                "header": [
                  {
                    "key": "Authorization",
                    "value": "Bearer {{access}}",
                    "type": "text"
                  }
                ],
                "url": {
                  "raw": "{{base_url}}/api/messaging/whatsapp/?bot={{bot_id}}",
                  "host": [
                    "{{base_url}}"
                  ],
                  "path": [
                    "api",
                    "messaging",
                    "whatsapp",
                    "?bot={{bot_id}}"
                  ]
                }
              },
              "response": []
            },
            {
              "name": "WA - Connect",
              "request": {
                "method": "POST",
                "header": [
                  {
                    "key": "Authorization",
                    "value": "Bearer {{access}}",
                    "type": "text"
                  },
                  {
                    "key": "Content-Type",
                    "value": "application/json",
                    "type": "text"
                  }
                ],
                "url": {
                  "raw": "{{base_url}}/api/messaging/whatsapp/",
                  "host": [
                    "{{base_url}}"
                  ],
                  "path": [
                    "api",
                    "messaging",
                    "whatsapp",
                    ""
                  ]
                },
                "body": {
                  "mode": "raw",
                  "raw": "{\n  \"bot_id\": \"{{bot_id}}\",\n  \"phone_number_id\": \"123456789\",\n  \"phone_number\": \"+447700123456\",\n  \"access_token\": \"EAAxxxxxxxx\"\n}",
                  "options": {
                    "raw": {
                      "language": "json"
                    }
                  }
                }
              },
              "response": []
            },
            {
              "name": "IG - Check Status",
              "request": {
                "method": "GET",
                "header": [
                  {
                    "key": "Authorization",
                    "value": "Bearer {{access}}",
                    "type": "text"
                  }
                ],
                "url": {
                  "raw": "{{base_url}}/api/messaging/instagram/?bot={{bot_id}}",
                  "host": [
                    "{{base_url}}"
                  ],
                  "path": [
                    "api",
                    "messaging",
                    "instagram",
                    "?bot={{bot_id}}"
                  ]
                }
              },
              "response": []
            },
            {
              "name": "IG - Connect",
              "request": {
                "method": "POST",
                "header": [
                  {
                    "key": "Authorization",
                    "value": "Bearer {{access}}",
                    "type": "text"
                  },
                  {
                    "key": "Content-Type",
                    "value": "application/json",
                    "type": "text"
                  }
                ],
                "url": {
                  "raw": "{{base_url}}/api/messaging/instagram/",
                  "host": [
                    "{{base_url}}"
                  ],
                  "path": [
                    "api",
                    "messaging",
                    "instagram",
                    ""
                  ]
                },
                "body": {
                  "mode": "raw",
                  "raw": "{\n  \"bot_id\": \"{{bot_id}}\",\n  \"instagram_account_id\": \"987654321\",\n  \"page_id\": \"123456789\",\n  \"page_access_token\": \"EAAxxxxxxxx\",\n  \"username\": \"johalstore\"\n}",
                  "options": {
                    "raw": {
                      "language": "json"
                    }
                  }
                }
              },
              "response": []
            }
          ]
        },
        {
          "name": "7b - Webhook Verify (NO AUTH)",
          "item": [
            {
              "name": "WA - Verify Webhook",
              "request": {
                "method": "GET",
                "header": [],
                "url": {
                  "raw": "{{base_url}}/api/messaging/whatsapp/webhook/?hub.verify_token=YOUR_VERIFY_TOKEN&hub.challenge=99999&hub.mode=subscribe",
                  "host": [
                    "{{base_url}}"
                  ],
                  "path": [
                    "api",
                    "messaging",
                    "whatsapp",
                    "webhook",
                    "?hub.verify_token=YOUR_VERIFY_TOKEN&hub.challenge=99999&hub.mode=subscribe"
                  ]
                }
              },
              "response": []
            },
            {
              "name": "FB - Verify Webhook",
              "request": {
                "method": "GET",
                "header": [],
                "url": {
                  "raw": "{{base_url}}/api/messaging/facebook/webhook/?hub.verify_token=YOUR_VERIFY_TOKEN&hub.challenge=88888&hub.mode=subscribe",
                  "host": [
                    "{{base_url}}"
                  ],
                  "path": [
                    "api",
                    "messaging",
                    "facebook",
                    "webhook",
                    "?hub.verify_token=YOUR_VERIFY_TOKEN&hub.challenge=88888&hub.mode=subscribe"
                  ]
                }
              },
              "response": []
            },
            {
              "name": "IG - Verify Webhook",
              "request": {
                "method": "GET",
                "header": [],
                "url": {
                  "raw": "{{base_url}}/api/messaging/instagram/webhook/?hub.verify_token=YOUR_VERIFY_TOKEN&hub.challenge=77777&hub.mode=subscribe",
                  "host": [
                    "{{base_url}}"
                  ],
                  "path": [
                    "api",
                    "messaging",
                    "instagram",
                    "webhook",
                    "?hub.verify_token=YOUR_VERIFY_TOKEN&hub.challenge=77777&hub.mode=subscribe"
                  ]
                }
              },
              "response": []
            }
          ]
        },
        {
          "name": "7c - Simulate Messages (NO AUTH)",
          "item": [
            {
              "name": "Simulate WA Message",
              "request": {
                "method": "POST",
                "header": [
                  {
                    "key": "Content-Type",
                    "value": "application/json",
                    "type": "text"
                  }
                ],
                "url": {
                  "raw": "{{base_url}}/api/messaging/whatsapp/webhook/",
                  "host": [
                    "{{base_url}}"
                  ],
                  "path": [
                    "api",
                    "messaging",
                    "whatsapp",
                    "webhook",
                    ""
                  ]
                },
                "body": {
                  "mode": "raw",
                  "raw": "{\n  \"entry\": [\n    {\n      \"changes\": [\n        {\n          \"value\": {\n            \"metadata\": {\n              \"phone_number_id\": \"123456789\"\n            },\n            \"messages\": [\n              {\n                \"from\": \"447700999888\",\n                \"type\": \"text\",\n                \"text\": {\n                  \"body\": \"Hello do you have iPhone 15 Pro in stock?\"\n                }\n              }\n            ]\n          }\n        }\n      ]\n    }\n  ]\n}",
                  "options": {
                    "raw": {
                      "language": "json"
                    }
                  }
                }
              },
              "response": []
            },
            {
              "name": "Simulate FB Message",
              "request": {
                "method": "POST",
                "header": [
                  {
                    "key": "Content-Type",
                    "value": "application/json",
                    "type": "text"
                  }
                ],
                "url": {
                  "raw": "{{base_url}}/api/messaging/facebook/webhook/",
                  "host": [
                    "{{base_url}}"
                  ],
                  "path": [
                    "api",
                    "messaging",
                    "facebook",
                    "webhook",
                    ""
                  ]
                },
                "body": {
                  "mode": "raw",
                  "raw": "{\n  \"entry\": [\n    {\n      \"messaging\": [\n        {\n          \"sender\": {\n            \"id\": \"PSID_123456\"\n          },\n          \"recipient\": {\n            \"id\": \"PAGE_123456789\"\n          },\n          \"message\": {\n            \"text\": \"Hi what are your store hours?\"\n          }\n        }\n      ]\n    }\n  ]\n}",
                  "options": {
                    "raw": {
                      "language": "json"
                    }
                  }
                }
              },
              "response": []
            }
          ]
        }
      ]
    },
    {
      "name": "8 - Analytics",
      "item": [
        {
          "name": "Insights Overview",
          "request": {
            "method": "GET",
            "header": [
              {
                "key": "Authorization",
                "value": "Bearer {{access}}",
                "type": "text"
              }
            ],
            "url": {
              "raw": "{{base_url}}/api/analytics/insights/?bot={{bot_id}}",
              "host": [
                "{{base_url}}"
              ],
              "path": [
                "api",
                "analytics",
                "insights",
                "?bot={{bot_id}}"
              ]
            }
          },
          "response": []
        },
        {
          "name": "Insights with Date Range",
          "request": {
            "method": "GET",
            "header": [
              {
                "key": "Authorization",
                "value": "Bearer {{access}}",
                "type": "text"
              }
            ],
            "url": {
              "raw": "{{base_url}}/api/analytics/insights/?bot={{bot_id}}&start=2026-01-01T00:00:00&end=2026-12-31T23:59:59",
              "host": [
                "{{base_url}}"
              ],
              "path": [
                "api",
                "analytics",
                "insights",
                "?bot={{bot_id}}&start=2026-01-01T00:00:00&end=2026-12-31T23:59:59"
              ]
            }
          },
          "response": []
        },
        {
          "name": "Customer Locations",
          "request": {
            "method": "GET",
            "header": [
              {
                "key": "Authorization",
                "value": "Bearer {{access}}",
                "type": "text"
              }
            ],
            "url": {
              "raw": "{{base_url}}/api/analytics/locations/?bot={{bot_id}}",
              "host": [
                "{{base_url}}"
              ],
              "path": [
                "api",
                "analytics",
                "locations",
                "?bot={{bot_id}}"
              ]
            }
          },
          "response": []
        },
        {
          "name": "Top Questions",
          "request": {
            "method": "GET",
            "header": [
              {
                "key": "Authorization",
                "value": "Bearer {{access}}",
                "type": "text"
              }
            ],
            "url": {
              "raw": "{{base_url}}/api/analytics/top-questions/?bot={{bot_id}}&limit=10",
              "host": [
                "{{base_url}}"
              ],
              "path": [
                "api",
                "analytics",
                "top-questions",
                "?bot={{bot_id}}&limit=10"
              ]
            }
          },
          "response": []
        },
        {
          "name": "Chats Over Time",
          "request": {
            "method": "GET",
            "header": [
              {
                "key": "Authorization",
                "value": "Bearer {{access}}",
                "type": "text"
              }
            ],
            "url": {
              "raw": "{{base_url}}/api/analytics/chats-over-time/?bot={{bot_id}}",
              "host": [
                "{{base_url}}"
              ],
              "path": [
                "api",
                "analytics",
                "chats-over-time",
                "?bot={{bot_id}}"
              ]
            }
          },
          "response": []
        },
        {
          "name": "Leads Summary",
          "request": {
            "method": "GET",
            "header": [
              {
                "key": "Authorization",
                "value": "Bearer {{access}}",
                "type": "text"
              }
            ],
            "url": {
              "raw": "{{base_url}}/api/analytics/leads/?bot={{bot_id}}",
              "host": [
                "{{base_url}}"
              ],
              "path": [
                "api",
                "analytics",
                "leads",
                "?bot={{bot_id}}"
              ]
            }
          },
          "response": []
        }
      ]
    },
    {
      "name": "9 - Billing",
      "item": [
        {
          "name": "Get Subscription",
          "request": {
            "method": "GET",
            "header": [
              {
                "key": "Authorization",
                "value": "Bearer {{access}}",
                "type": "text"
              }
            ],
            "url": {
              "raw": "{{base_url}}/api/billing/subscription/",
              "host": [
                "{{base_url}}"
              ],
              "path": [
                "api",
                "billing",
                "subscription",
                ""
              ]
            }
          },
          "response": []
        },
        {
          "name": "Create Checkout - Smart Plan",
          "request": {
            "method": "POST",
            "header": [
              {
                "key": "Authorization",
                "value": "Bearer {{access}}",
                "type": "text"
              },
              {
                "key": "Content-Type",
                "value": "application/json",
                "type": "text"
              }
            ],
            "url": {
              "raw": "{{base_url}}/api/billing/checkout/",
              "host": [
                "{{base_url}}"
              ],
              "path": [
                "api",
                "billing",
                "checkout",
                ""
              ]
            },
            "body": {
              "mode": "raw",
              "raw": "{\n  \"plan\": \"smart\",\n  \"success_url\": \"http://localhost:3000/billing/success\",\n  \"cancel_url\": \"http://localhost:3000/billing/cancel\"\n}",
              "options": {
                "raw": {
                  "language": "json"
                }
              }
            }
          },
          "response": []
        },
        {
          "name": "Create Checkout - Boost Plan",
          "request": {
            "method": "POST",
            "header": [
              {
                "key": "Authorization",
                "value": "Bearer {{access}}",
                "type": "text"
              },
              {
                "key": "Content-Type",
                "value": "application/json",
                "type": "text"
              }
            ],
            "url": {
              "raw": "{{base_url}}/api/billing/checkout/",
              "host": [
                "{{base_url}}"
              ],
              "path": [
                "api",
                "billing",
                "checkout",
                ""
              ]
            },
            "body": {
              "mode": "raw",
              "raw": "{\n  \"plan\": \"boost\",\n  \"success_url\": \"http://localhost:3000/billing/success\",\n  \"cancel_url\": \"http://localhost:3000/billing/cancel\"\n}",
              "options": {
                "raw": {
                  "language": "json"
                }
              }
            }
          },
          "response": []
        },
        {
          "name": "Open Billing Portal",
          "request": {
            "method": "POST",
            "header": [
              {
                "key": "Authorization",
                "value": "Bearer {{access}}",
                "type": "text"
              },
              {
                "key": "Content-Type",
                "value": "application/json",
                "type": "text"
              }
            ],
            "url": {
              "raw": "{{base_url}}/api/billing/portal/",
              "host": [
                "{{base_url}}"
              ],
              "path": [
                "api",
                "billing",
                "portal",
                ""
              ]
            },
            "body": {
              "mode": "raw",
              "raw": "{\n  \"return_url\": \"http://localhost:3000/billing\"\n}",
              "options": {
                "raw": {
                  "language": "json"
                }
              }
            }
          },
          "response": []
        },
        {
          "name": "List Invoices",
          "request": {
            "method": "GET",
            "header": [
              {
                "key": "Authorization",
                "value": "Bearer {{access}}",
                "type": "text"
              }
            ],
            "url": {
              "raw": "{{base_url}}/api/billing/invoices/",
              "host": [
                "{{base_url}}"
              ],
              "path": [
                "api",
                "billing",
                "invoices",
                ""
              ]
            }
          },
          "response": []
        }
      ]
    }
  ]
}